odoo/addons/pos_customer_required_fields/README.rst
odoo/addons/pos_customer_required_fields/__init__.py
odoo/addons/pos_customer_required_fields/__manifest__.py
odoo/addons/pos_customer_required_fields/i18n/fr.po
odoo/addons/pos_customer_required_fields/i18n/pos_customer_required_fields.pot
odoo/addons/pos_customer_required_fields/models/__init__.py
odoo/addons/pos_customer_required_fields/models/pos_config.py
odoo/addons/pos_customer_required_fields/models/res_partner.py
odoo/addons/pos_customer_required_fields/readme/CONFIGURE.rst
odoo/addons/pos_customer_required_fields/readme/CONTRIBUTORS.rst
odoo/addons/pos_customer_required_fields/readme/DESCRIPTION.rst
odoo/addons/pos_customer_required_fields/readme/USAGE.rst
odoo/addons/pos_customer_required_fields/static/description/icon.png
odoo/addons/pos_customer_required_fields/static/description/index.html
odoo/addons/pos_customer_required_fields/static/description/pos_customer_missing_fields.png
odoo/addons/pos_customer_required_fields/static/description/pos_edit_customer.png
odoo/addons/pos_customer_required_fields/static/src/css/pos.css
odoo/addons/pos_customer_required_fields/static/src/js/screens.js
odoo/addons/pos_customer_required_fields/static/src/xml/pos.xml
odoo/addons/pos_customer_required_fields/templates/assets.xml
odoo/addons/pos_customer_required_fields/tests/__init__.py
odoo/addons/pos_customer_required_fields/tests/test_res_partner.py
odoo/addons/pos_customer_required_fields/views/view_pos_config.xml
odoo12_addon_pos_customer_required_fields-12.0.1.0.1.dist-info/METADATA
odoo12_addon_pos_customer_required_fields-12.0.1.0.1.dist-info/WHEEL
odoo12_addon_pos_customer_required_fields-12.0.1.0.1.dist-info/top_level.txt
odoo12_addon_pos_customer_required_fields-12.0.1.0.1.dist-info/RECORD
